digen/__init__.py
digen/benchmark.py
digen/chartsdata.pkl
digen/dataset.py
digen/defaults.py
digen/profiling.py
digen/stats.csv
digen-0.0.5.dist-info/LICENSE
digen-0.0.5.dist-info/METADATA
digen-0.0.5.dist-info/WHEEL
digen-0.0.5.dist-info/top_level.txt
digen-0.0.5.dist-info/zip-safe
digen-0.0.5.dist-info/RECORD
