Metadata-Version: 2.1
Name: digen
Version: 0.0.5
Summary: DIGEN: Diverse Generative ML Benchmark
Home-page: https://github.com/EpistasisLab/digen
Author: Patryk Orzechowski
Author-email: patryk.orzechowski@gmail.com
License: UNKNOWN
Keywords: data mining,benchmark,machine learning,data analysis,datasets,data science
Platform: UNKNOWN
Classifier: Development Status :: 3 - Alpha
Classifier: Intended Audience :: Developers
Classifier: Intended Audience :: Information Technology
Classifier: Intended Audience :: Science/Research
Classifier: License :: OSI Approved :: MIT License
Classifier: Programming Language :: Python :: 3.7
Classifier: Programming Language :: Python :: 3.8
Classifier: Programming Language :: Python :: 3.9
Classifier: Topic :: Scientific/Engineering
Classifier: Topic :: Scientific/Engineering :: Mathematics
Classifier: Topic :: Scientific/Engineering :: Artificial Intelligence
Classifier: Topic :: Scientific/Engineering :: Bio-Informatics
Classifier: Topic :: Scientific/Engineering :: Information Analysis
Classifier: Topic :: Software Development
Classifier: Topic :: Software Development :: Libraries
Classifier: Topic :: Software Development :: Libraries :: Python Modules
Classifier: Topic :: Utilities
Requires-Dist: deap (>=1.3.0)
Requires-Dist: importlib-resources
Requires-Dist: lightgbm (>=3.1.1)
Requires-Dist: matplotlib
Requires-Dist: numpy (>=1.21)
Requires-Dist: optuna (>=1.3.0)
Requires-Dist: pandas (>=1.0.5)
Requires-Dist: requests
Requires-Dist: scikit-learn (>=0.22.2)
Requires-Dist: seaborn (>=0.11.2)
Requires-Dist: xgboost (>=1.3.2)
Provides-Extra: dev
Requires-Dist: pandas-profiling ; extra == 'dev'
Requires-Dist: scipy ; extra == 'dev'
